{
    "sourceFile": "components/carList.js",
    "activeCommit": 0,
    "commits": [
        {
            "activePatchIndex": 7,
            "patches": [
                {
                    "date": 1758175270769,
                    "content": "Index: \n===================================================================\n--- \n+++ \n"
                },
                {
                    "date": 1758175588589,
                    "content": "Index: \n===================================================================\n--- \n+++ \n@@ -82,7 +82,54 @@\n     name: \"Land Rover\",\r\n     models: [\"Range Rover\", \"Range Rover Sport\", \"Range Rover Velar\", \"Defender\", \"Discovery\"],\r\n   },\r\n   { name: \"Mitsubishi\", models: [\"Outlander\", \"Eclipse Cross\", \"Mirage\", \"RVR\"] },\r\n+  // Add these to carList.js\r\n+\r\n+{\r\n+  name: \"Dodge\",\r\n+  models: [\"Charger\", \"Challenger\", \"Durango\", \"Hornet\", \"Journey\", \"Caravan\"],\r\n+},\r\n+{\r\n+  name: \"Infiniti\",\r\n+  models: [\"Q50\", \"Q60\", \"QX50\", \"QX60\", \"QX80\"],\r\n+},\r\n+{\r\n+  name: \"Lincoln\",\r\n+  models: [\"Navigator\", \"Aviator\", \"Corsair\", \"Nautilus\"],\r\n+},\r\n+{\r\n+  name: \"Cadillac\",\r\n+  models: [\"Escalade\", \"XT5\", \"XT6\", \"Lyriq\", \"CT5\", \"CT4\"],\r\n+},\r\n+{\r\n+  name: \"Genesis\",\r\n+  models: [\"G70\", \"G80\", \"G90\", \"GV70\", \"GV80\"],\r\n+},\r\n+{\r\n+  name: \"Alfa Romeo\",\r\n+  models: [\"Giulia\", \"Stelvio\", \"Tonale\", \"4C\"],\r\n+},\r\n+{\r\n+  name: \"Mini\",\r\n+  models: [\"Cooper\", \"Clubman\", \"Countryman\", \"Hardtop\"],\r\n+},\r\n+{\r\n+  name: \"Fiat\",\r\n+  models: [\"500\", \"500X\", \"500e\", \"124 Spider\"],\r\n+},\r\n+{\r\n+  name: \"Peugeot\",\r\n+  models: [\"208\", \"2008\", \"3008\", \"5008\"],\r\n+},\r\n+{\r\n+  name: \"Renault\",\r\n+  models: [\"Clio\", \"Megane\", \"Captur\", \"Kadjar\", \"Koleos\"],\r\n+},\r\n+{\r\n+  name: \"Suzuki\",\r\n+  models: [\"Swift\", \"Vitara\", \"Jimny\", \"SX4\"],\r\n+},\r\n+\r\n ];\r\n \r\n export default carList;\r\n"
                },
                {
                    "date": 1758175594047,
                    "content": "Index: \n===================================================================\n--- \n+++ \n@@ -0,0 +1,327 @@\n+// carList.js\r\n+const carList = [\r\n+    {\r\n+        name: \"Honda\",\r\n+        models: [\r\n+            \"Civic\",\r\n+            \"Accord\",\r\n+            \"CR-V\",\r\n+            \"HR-V\",\r\n+            \"Pilot\",\r\n+            \"Odyssey\",\r\n+            \"Ridgeline\",\r\n+            \"Insight\",\r\n+            \"Passport\",\r\n+            \"Fit\",\r\n+        ],\r\n+    },\r\n+    {\r\n+        name: \"Toyota\",\r\n+        models: [\r\n+            \"Corolla\",\r\n+            \"Camry\",\r\n+            \"RAV4\",\r\n+            \"Highlander\",\r\n+            \"Tacoma\",\r\n+            \"Prius\",\r\n+            \"Sienna\",\r\n+            \"Tundra\",\r\n+            \"Sequoia\",\r\n+            \"Avalon\",\r\n+            \"4Runner\",\r\n+        ],\r\n+    },\r\n+    {\r\n+        name: \"Ford\",\r\n+        models: [\r\n+            \"F-150\",\r\n+            \"Escape\",\r\n+            \"Mustang\",\r\n+            \"Explorer\",\r\n+            \"Edge\",\r\n+            \"Super Duty\",\r\n+            \"Bronco\",\r\n+            \"Expedition\",\r\n+            \"Maverick\",\r\n+            \"Fusion\",\r\n+        ],\r\n+    },\r\n+    {\r\n+        name: \"Chevrolet\",\r\n+        models: [\r\n+            \"Silverado\",\r\n+            \"Equinox\",\r\n+            \"Malibu\",\r\n+            \"Traverse\",\r\n+            \"Colorado\",\r\n+            \"Bolt EV\",\r\n+            \"Spark\",\r\n+            \"Tahoe\",\r\n+            \"Suburban\",\r\n+            \"Blazer\",\r\n+        ],\r\n+    },\r\n+    {\r\n+        name: \"Hyundai\",\r\n+        models: [\r\n+            \"Kona\",\r\n+            \"Elantra\",\r\n+            \"Tucson\",\r\n+            \"Santa Fe\",\r\n+            \"Palisade\",\r\n+            \"Ioniq\",\r\n+            \"Veloster\",\r\n+            \"Sonata\",\r\n+            \"Venue\",\r\n+        ],\r\n+    },\r\n+    {\r\n+        name: \"Nissan\",\r\n+        models: [\r\n+            \"Rogue\",\r\n+            \"Altima\",\r\n+            \"Sentra\",\r\n+            \"Murano\",\r\n+            \"Frontier\",\r\n+            \"Leaf\",\r\n+            \"Kicks\",\r\n+            \"Titan\",\r\n+            \"Pathfinder\",\r\n+            \"Maxima\",\r\n+            \"Armada\",\r\n+        ],\r\n+    },\r\n+    { name: \"Ram\", models: [\"1500\", \"2500\", \"3500\", \"ProMaster\"] },\r\n+    { name: \"GMC\", models: [\"Sierra\", \"Canyon\", \"Terrain\", \"Acadia\", \"Yukon\"] },\r\n+    {\r\n+        name: \"Kia\",\r\n+        models: [\r\n+            \"Sorento\",\r\n+            \"Sportage\",\r\n+            \"Telluride\",\r\n+            \"Forte\",\r\n+            \"Soul\",\r\n+            \"K5\",\r\n+            \"Carnival\",\r\n+            \"Seltos\",\r\n+        ],\r\n+    },\r\n+    {\r\n+        name: \"Mazda\",\r\n+        models: [\r\n+            \"CX-5\",\r\n+            \"Mazda3\",\r\n+            \"CX-30\",\r\n+            \"Mazda6\",\r\n+            \"CX-9\",\r\n+            \"MX-5\",\r\n+            \"CX-50\",\r\n+            \"CX-90\",\r\n+        ],\r\n+    },\r\n+    {\r\n+        name: \"Volkswagen\",\r\n+        models: [\r\n+            \"Jetta\",\r\n+            \"Golf\",\r\n+            \"Tiguan\",\r\n+            \"Passat\",\r\n+            \"ID.4\",\r\n+            \"ID. Buzz\",\r\n+            \"Arteon\",\r\n+            \"Atlas\",\r\n+        ],\r\n+    },\r\n+    {\r\n+        name: \"BMW\",\r\n+        models: [\r\n+            \"3 Series\",\r\n+            \"X5\",\r\n+            \"X3\",\r\n+            \"5 Series\",\r\n+            \"X7\",\r\n+            \"i4\",\r\n+            \"iX\",\r\n+            \"i3\",\r\n+            \"M3\",\r\n+            \"M5\",\r\n+        ],\r\n+    },\r\n+    {\r\n+        name: \"Mercedes-Benz\",\r\n+        models: [\r\n+            \"C-Class\",\r\n+            \"GLC\",\r\n+            \"E-Class\",\r\n+            \"GLS\",\r\n+            \"EQB\",\r\n+            \"EQS\",\r\n+            \"EQE\",\r\n+            \"EQC\",\r\n+            \"S-Class\",\r\n+            \"A-Class\",\r\n+        ],\r\n+    },\r\n+    {\r\n+        name: \"Audi\",\r\n+        models: [\r\n+            \"A4\",\r\n+            \"Q5\",\r\n+            \"A3\",\r\n+            \"Q7\",\r\n+            \"e-tron\",\r\n+            \"Q4 e-tron\",\r\n+            \"Q5 e-tron\",\r\n+            \"A6 e-tron\",\r\n+            \"A8\",\r\n+        ],\r\n+    },\r\n+    {\r\n+        name: \"Tesla\",\r\n+        models: [\r\n+            \"Model 3\",\r\n+            \"Model Y\",\r\n+            \"Model S\",\r\n+            \"Model X\",\r\n+            \"Cybertruck\",\r\n+            \"Roadster\",\r\n+            \"Model S Plaid\",\r\n+        ],\r\n+    },\r\n+    {\r\n+        name: \"Jeep\",\r\n+        models: [\r\n+            \"Grand Cherokee\",\r\n+            \"Cherokee\",\r\n+            \"Wrangler\",\r\n+            \"Compass\",\r\n+            \"Gladiator\",\r\n+            \"Wagoneer\",\r\n+            \"Grand Wagoneer\",\r\n+            \"Renegade\",\r\n+        ],\r\n+    },\r\n+    {\r\n+        name: \"Subaru\",\r\n+        models: [\r\n+            \"Outback\",\r\n+            \"Forester\",\r\n+            \"Impreza\",\r\n+            \"Crosstrek\",\r\n+            \"Ascent\",\r\n+            \"WRX\",\r\n+            \"BRZ\",\r\n+            \"Legacy\",\r\n+        ],\r\n+    },\r\n+    {\r\n+        name: \"Chrysler\",\r\n+        models: [\r\n+            \"Pacifica\",\r\n+            \"Voyager\",\r\n+            \"Grand Caravan\",\r\n+            \"300\",\r\n+            \"Aspen\",\r\n+            \"Pacifica Hybrid\",\r\n+        ],\r\n+    },\r\n+    {\r\n+        name: \"Buick\",\r\n+        models: [\r\n+            \"Envision\",\r\n+            \"Encore\",\r\n+            \"Enclave\",\r\n+            \"Regal\",\r\n+            \"Cascada\",\r\n+            \"Verano\",\r\n+            \"Encore GX\",\r\n+        ],\r\n+    },\r\n+    { name: \"Lexus\", models: [\"RX\", \"NX\", \"ES\", \"UX\", \"GX\", \"LX\", \"LC\", \"IS\"] },\r\n+    {\r\n+        name: \"Porsche\",\r\n+        models: [\r\n+            \"911\",\r\n+            \"Macan\",\r\n+            \"Cayenne\",\r\n+            \"Taycan\",\r\n+            \"718 Cayman\",\r\n+            \"718 Boxster\",\r\n+            \"Panamera\",\r\n+        ],\r\n+    },\r\n+    { name: \"Acura\", models: [\"MDX\", \"RDX\", \"TLX\", \"ILX\", \"Integra\", \"NSX\"] },\r\n+    { name: \"Volvo\", models: [\"XC40\", \"XC60\", \"XC90\", \"S60\", \"S90\", \"V60\"] },\r\n+    {\r\n+        name: \"Jaguar\",\r\n+        models: [\"F-Pace\", \"E-Pace\", \"I-Pace\", \"XF\", \"XE\", \"F-Type\"],\r\n+    },\r\n+    {\r\n+        name: \"Land Rover\",\r\n+        models: [\r\n+            \"Range Rover\",\r\n+            \"Range Rover Sport\",\r\n+            \"Range Rover Velar\",\r\n+            \"Defender\",\r\n+            \"Discovery\",\r\n+        ],\r\n+    },\r\n+    {\r\n+        name: \"Mitsubishi\",\r\n+        models: [\"Outlander\", \"Eclipse Cross\", \"Mirage\", \"RVR\"],\r\n+    },\r\n+\r\n+    {\r\n+        name: \"Dodge\",\r\n+        models: [\r\n+            \"Charger\",\r\n+            \"Challenger\",\r\n+            \"Durango\",\r\n+            \"Hornet\",\r\n+            \"Journey\",\r\n+            \"Caravan\",\r\n+        ],\r\n+    },\r\n+    {\r\n+        name: \"Infiniti\",\r\n+        models: [\"Q50\", \"Q60\", \"QX50\", \"QX60\", \"QX80\"],\r\n+    },\r\n+    {\r\n+        name: \"Lincoln\",\r\n+        models: [\"Navigator\", \"Aviator\", \"Corsair\", \"Nautilus\"],\r\n+    },\r\n+    {\r\n+        name: \"Cadillac\",\r\n+        models: [\"Escalade\", \"XT5\", \"XT6\", \"Lyriq\", \"CT5\", \"CT4\"],\r\n+    },\r\n+    {\r\n+        name: \"Genesis\",\r\n+        models: [\"G70\", \"G80\", \"G90\", \"GV70\", \"GV80\"],\r\n+    },\r\n+    {\r\n+        name: \"Alfa Romeo\",\r\n+        models: [\"Giulia\", \"Stelvio\", \"Tonale\", \"4C\"],\r\n+    },\r\n+    {\r\n+        name: \"Mini\",\r\n+        models: [\"Cooper\", \"Clubman\", \"Countryman\", \"Hardtop\"],\r\n+    },\r\n+    {\r\n+        name: \"Fiat\",\r\n+        models: [\"500\", \"500X\", \"500e\", \"124 Spider\"],\r\n+    },\r\n+    {\r\n+        name: \"Peugeot\",\r\n+        models: [\"208\", \"2008\", \"3008\", \"5008\"],\r\n+    },\r\n+    {\r\n+        name: \"Renault\",\r\n+        models: [\"Clio\", \"Megane\", \"Captur\", \"Kadjar\", \"Koleos\"],\r\n+    },\r\n+    {\r\n+        name: \"Suzuki\",\r\n+        models: [\"Swift\", \"Vitara\", \"Jimny\", \"SX4\"],\r\n+    },\r\n+];\r\n+\r\n+export default carList;\r\n"
                },
                {
                    "date": 1758175644683,
                    "content": "Index: \n===================================================================\n--- \n+++ \n@@ -0,0 +1,392 @@\n+// carList.js\r\n+const carList = [\r\n+    {\r\n+        name: \"Honda\",\r\n+        models: [\r\n+            \"Civic\",\r\n+            \"Accord\",\r\n+            \"CR-V\",\r\n+            \"HR-V\",\r\n+            \"Pilot\",\r\n+            \"Odyssey\",\r\n+            \"Ridgeline\",\r\n+            \"Insight\",\r\n+            \"Passport\",\r\n+            \"Fit\",\r\n+        ],\r\n+    },\r\n+    {\r\n+        name: \"Toyota\",\r\n+        models: [\r\n+            \"Corolla\",\r\n+            \"Camry\",\r\n+            \"RAV4\",\r\n+            \"Highlander\",\r\n+            \"Tacoma\",\r\n+            \"Prius\",\r\n+            \"Sienna\",\r\n+            \"Tundra\",\r\n+            \"Sequoia\",\r\n+            \"Avalon\",\r\n+            \"4Runner\",\r\n+        ],\r\n+    },\r\n+    {\r\n+        name: \"Ford\",\r\n+        models: [\r\n+            \"F-150\",\r\n+            \"Escape\",\r\n+            \"Mustang\",\r\n+            \"Explorer\",\r\n+            \"Edge\",\r\n+            \"Super Duty\",\r\n+            \"Bronco\",\r\n+            \"Expedition\",\r\n+            \"Maverick\",\r\n+            \"Fusion\",\r\n+        ],\r\n+    },\r\n+    {\r\n+        name: \"Chevrolet\",\r\n+        models: [\r\n+            \"Silverado\",\r\n+            \"Equinox\",\r\n+            \"Malibu\",\r\n+            \"Traverse\",\r\n+            \"Colorado\",\r\n+            \"Bolt EV\",\r\n+            \"Spark\",\r\n+            \"Tahoe\",\r\n+            \"Suburban\",\r\n+            \"Blazer\",\r\n+        ],\r\n+    },\r\n+    {\r\n+        name: \"Hyundai\",\r\n+        models: [\r\n+            \"Kona\",\r\n+            \"Elantra\",\r\n+            \"Tucson\",\r\n+            \"Santa Fe\",\r\n+            \"Palisade\",\r\n+            \"Ioniq\",\r\n+            \"Veloster\",\r\n+            \"Sonata\",\r\n+            \"Venue\",\r\n+        ],\r\n+    },\r\n+    {\r\n+        name: \"Nissan\",\r\n+        models: [\r\n+            \"Rogue\",\r\n+            \"Altima\",\r\n+            \"Sentra\",\r\n+            \"Murano\",\r\n+            \"Frontier\",\r\n+            \"Leaf\",\r\n+            \"Kicks\",\r\n+            \"Titan\",\r\n+            \"Pathfinder\",\r\n+            \"Maxima\",\r\n+            \"Armada\",\r\n+        ],\r\n+    },\r\n+    { name: \"Ram\", models: [\"1500\", \"2500\", \"3500\", \"ProMaster\"] },\r\n+    { name: \"GMC\", models: [\"Sierra\", \"Canyon\", \"Terrain\", \"Acadia\", \"Yukon\"] },\r\n+    {\r\n+        name: \"Kia\",\r\n+        models: [\r\n+            \"Sorento\",\r\n+            \"Sportage\",\r\n+            \"Telluride\",\r\n+            \"Forte\",\r\n+            \"Soul\",\r\n+            \"K5\",\r\n+            \"Carnival\",\r\n+            \"Seltos\",\r\n+        ],\r\n+    },\r\n+    {\r\n+        name: \"Mazda\",\r\n+        models: [\r\n+            \"CX-5\",\r\n+            \"Mazda3\",\r\n+            \"CX-30\",\r\n+            \"Mazda6\",\r\n+            \"CX-9\",\r\n+            \"MX-5\",\r\n+            \"CX-50\",\r\n+            \"CX-90\",\r\n+        ],\r\n+    },\r\n+    {\r\n+        name: \"Volkswagen\",\r\n+        models: [\r\n+            \"Jetta\",\r\n+            \"Golf\",\r\n+            \"Tiguan\",\r\n+            \"Passat\",\r\n+            \"ID.4\",\r\n+            \"ID. Buzz\",\r\n+            \"Arteon\",\r\n+            \"Atlas\",\r\n+        ],\r\n+    },\r\n+    {\r\n+        name: \"BMW\",\r\n+        models: [\r\n+            \"3 Series\",\r\n+            \"X5\",\r\n+            \"X3\",\r\n+            \"5 Series\",\r\n+            \"X7\",\r\n+            \"i4\",\r\n+            \"iX\",\r\n+            \"i3\",\r\n+            \"M3\",\r\n+            \"M5\",\r\n+        ],\r\n+    },\r\n+    {\r\n+        name: \"Mercedes-Benz\",\r\n+        models: [\r\n+            \"C-Class\",\r\n+            \"GLC\",\r\n+            \"E-Class\",\r\n+            \"GLS\",\r\n+            \"EQB\",\r\n+            \"EQS\",\r\n+            \"EQE\",\r\n+            \"EQC\",\r\n+            \"S-Class\",\r\n+            \"A-Class\",\r\n+        ],\r\n+    },\r\n+    {\r\n+        name: \"Audi\",\r\n+        models: [\r\n+            \"A4\",\r\n+            \"Q5\",\r\n+            \"A3\",\r\n+            \"Q7\",\r\n+            \"e-tron\",\r\n+            \"Q4 e-tron\",\r\n+            \"Q5 e-tron\",\r\n+            \"A6 e-tron\",\r\n+            \"A8\",\r\n+        ],\r\n+    },\r\n+    {\r\n+        name: \"Tesla\",\r\n+        models: [\r\n+            \"Model 3\",\r\n+            \"Model Y\",\r\n+            \"Model S\",\r\n+            \"Model X\",\r\n+            \"Cybertruck\",\r\n+            \"Roadster\",\r\n+            \"Model S Plaid\",\r\n+        ],\r\n+    },\r\n+    {\r\n+        name: \"Jeep\",\r\n+        models: [\r\n+            \"Grand Cherokee\",\r\n+            \"Cherokee\",\r\n+            \"Wrangler\",\r\n+            \"Compass\",\r\n+            \"Gladiator\",\r\n+            \"Wagoneer\",\r\n+            \"Grand Wagoneer\",\r\n+            \"Renegade\",\r\n+        ],\r\n+    },\r\n+    {\r\n+        name: \"Subaru\",\r\n+        models: [\r\n+            \"Outback\",\r\n+            \"Forester\",\r\n+            \"Impreza\",\r\n+            \"Crosstrek\",\r\n+            \"Ascent\",\r\n+            \"WRX\",\r\n+            \"BRZ\",\r\n+            \"Legacy\",\r\n+        ],\r\n+    },\r\n+    {\r\n+        name: \"Chrysler\",\r\n+        models: [\r\n+            \"Pacifica\",\r\n+            \"Voyager\",\r\n+            \"Grand Caravan\",\r\n+            \"300\",\r\n+            \"Aspen\",\r\n+            \"Pacifica Hybrid\",\r\n+        ],\r\n+    },\r\n+    {\r\n+        name: \"Buick\",\r\n+        models: [\r\n+            \"Envision\",\r\n+            \"Encore\",\r\n+            \"Enclave\",\r\n+            \"Regal\",\r\n+            \"Cascada\",\r\n+            \"Verano\",\r\n+            \"Encore GX\",\r\n+        ],\r\n+    },\r\n+    { name: \"Lexus\", models: [\"RX\", \"NX\", \"ES\", \"UX\", \"GX\", \"LX\", \"LC\", \"IS\"] },\r\n+    {\r\n+        name: \"Porsche\",\r\n+        models: [\r\n+            \"911\",\r\n+            \"Macan\",\r\n+            \"Cayenne\",\r\n+            \"Taycan\",\r\n+            \"718 Cayman\",\r\n+            \"718 Boxster\",\r\n+            \"Panamera\",\r\n+        ],\r\n+    },\r\n+    { name: \"Acura\", models: [\"MDX\", \"RDX\", \"TLX\", \"ILX\", \"Integra\", \"NSX\"] },\r\n+    { name: \"Volvo\", models: [\"XC40\", \"XC60\", \"XC90\", \"S60\", \"S90\", \"V60\"] },\r\n+    {\r\n+        name: \"Jaguar\",\r\n+        models: [\"F-Pace\", \"E-Pace\", \"I-Pace\", \"XF\", \"XE\", \"F-Type\"],\r\n+    },\r\n+    {\r\n+        name: \"Land Rover\",\r\n+        models: [\r\n+            \"Range Rover\",\r\n+            \"Range Rover Sport\",\r\n+            \"Range Rover Velar\",\r\n+            \"Defender\",\r\n+            \"Discovery\",\r\n+        ],\r\n+    },\r\n+    {\r\n+        name: \"Mitsubishi\",\r\n+        models: [\"Outlander\", \"Eclipse Cross\", \"Mirage\", \"RVR\"],\r\n+    },\r\n+\r\n+    {\r\n+        name: \"Dodge\",\r\n+        models: [\r\n+            \"Charger\",\r\n+            \"Challenger\",\r\n+            \"Durango\",\r\n+            \"Hornet\",\r\n+            \"Journey\",\r\n+            \"Caravan\",\r\n+        ],\r\n+    },\r\n+    {\r\n+        name: \"Infiniti\",\r\n+        models: [\"Q50\", \"Q60\", \"QX50\", \"QX60\", \"QX80\"],\r\n+    },\r\n+    {\r\n+        name: \"Lincoln\",\r\n+        models: [\"Navigator\", \"Aviator\", \"Corsair\", \"Nautilus\"],\r\n+    },\r\n+    {\r\n+        name: \"Cadillac\",\r\n+        models: [\"Escalade\", \"XT5\", \"XT6\", \"Lyriq\", \"CT5\", \"CT4\"],\r\n+    },\r\n+    {\r\n+        name: \"Genesis\",\r\n+        models: [\"G70\", \"G80\", \"G90\", \"GV70\", \"GV80\"],\r\n+    },\r\n+    {\r\n+        name: \"Alfa Romeo\",\r\n+        models: [\"Giulia\", \"Stelvio\", \"Tonale\", \"4C\"],\r\n+    },\r\n+    {\r\n+        name: \"Mini\",\r\n+        models: [\"Cooper\", \"Clubman\", \"Countryman\", \"Hardtop\"],\r\n+    },\r\n+    {\r\n+        name: \"Fiat\",\r\n+        models: [\"500\", \"500X\", \"500e\", \"124 Spider\"],\r\n+    },\r\n+    {\r\n+        name: \"Peugeot\",\r\n+        models: [\"208\", \"2008\", \"3008\", \"5008\"],\r\n+    },\r\n+    {\r\n+        name: \"Renault\",\r\n+        models: [\"Clio\", \"Megane\", \"Captur\", \"Kadjar\", \"Koleos\"],\r\n+    },\r\n+    {\r\n+        name: \"Suzuki\",\r\n+        models: [\"Swift\", \"Vitara\", \"Jimny\", \"SX4\"],\r\n+    },\r\n+    {\r\n+  name: \"Maserati\",\r\n+  models: [\"Ghibli\", \"Quattroporte\", \"Levante\", \"MC20\", \"GranTurismo\"],\r\n+},\r\n+{\r\n+  name: \"Ferrari\",\r\n+  models: [\"488\", \"F8 Tributo\", \"Roma\", \"Portofino\", \"SF90 Stradale\"],\r\n+},\r\n+{\r\n+  name: \"Lamborghini\",\r\n+  models: [\"Huracán\", \"Aventador\", \"Urus\", \"Revuelto\", \"Gallardo\"],\r\n+},\r\n+{\r\n+  name: \"Aston Martin\",\r\n+  models: [\"DB11\", \"DBS\", \"Vantage\", \"DBX\", \"Valhalla\"],\r\n+},\r\n+{\r\n+  name: \"Bentley\",\r\n+  models: [\"Continental GT\", \"Flying Spur\", \"Bentayga\", \"Mulsanne\"],\r\n+},\r\n+{\r\n+  name: \"Rolls-Royce\",\r\n+  models: [\"Phantom\", \"Ghost\", \"Cullinan\", \"Wraith\", \"Dawn\"],\r\n+},\r\n+{\r\n+  name: \"Bugatti\",\r\n+  models: [\"Chiron\", \"Veyron\", \"Divo\", \"Bolide\"],\r\n+},\r\n+{\r\n+  name: \"McLaren\",\r\n+  models: [\"720S\", \"570S\", \"Artura\", \"P1\", \"GT\"],\r\n+},\r\n+{\r\n+  name: \"Polestar\",\r\n+  models: [\"Polestar 2\", \"Polestar 3\", \"Polestar 4\", \"Polestar 5\"],\r\n+},\r\n+{\r\n+  name: \"Lucid\",\r\n+  models: [\"Air\", \"Gravity\"],\r\n+},\r\n+{\r\n+  name: \"Rivian\",\r\n+  models: [\"R1T\", \"R1S\"],\r\n+},\r\n+{\r\n+  name: \"BYD\",\r\n+  models: [\"Tang\", \"Han\", \"Atto 3\", \"Dolphin\", \"Seal\"],\r\n+},\r\n+{\r\n+  name: \"Chery\",\r\n+  models: [\"Tiggo 4\", \"Tiggo 7\", \"Tiggo 8\", \"Arrizo 5\"],\r\n+},\r\n+{\r\n+  name: \"Geely\",\r\n+  models: [\"Coolray\", \"Emgrand\", \"Atlas\", \"Preface\"],\r\n+},\r\n+{\r\n+  name: \"Mahindra\",\r\n+  models: [\"XUV700\", \"Scorpio\", \"Bolero\", \"Thar\"],\r\n+},\r\n+{\r\n+  name: \"Tata\",\r\n+  models: [\"Nexon\", \"Harrier\", \"Safari\", \"Altroz\", \"Punch\"],\r\n+},\r\n+\r\n+];\r\n+\r\n+export default carList;\r\n"
                },
                {
                    "date": 1758175661376,
                    "content": "Index: \n===================================================================\n--- \n+++ \n@@ -385,8 +385,88 @@\n {\r\n   name: \"Tata\",\r\n   models: [\"Nexon\", \"Harrier\", \"Safari\", \"Altroz\", \"Punch\"],\r\n },\r\n+{\r\n+  name: \"Citroën\",\r\n+  models: [\"C3\", \"C4\", \"C5 Aircross\", \"Berlingo\", \"Ami\"],\r\n+},\r\n+{\r\n+  name: \"Opel\",\r\n+  models: [\"Corsa\", \"Astra\", \"Mokka\", \"Insignia\", \"Crossland\"],\r\n+},\r\n+{\r\n+  name: \"Vauxhall\",\r\n+  models: [\"Corsa\", \"Astra\", \"Mokka\", \"Crossland\"], // UK versions of Opel\r\n+},\r\n+{\r\n+  name: \"Skoda\",\r\n+  models: [\"Octavia\", \"Superb\", \"Kodiaq\", \"Kamiq\", \"Fabia\"],\r\n+},\r\n+{\r\n+  name: \"Seat\",\r\n+  models: [\"Ibiza\", \"Leon\", \"Ateca\", \"Arona\", \"Tarraco\"],\r\n+},\r\n+{\r\n+  name: \"Dacia\",\r\n+  models: [\"Duster\", \"Sandero\", \"Logan\", \"Jogger\"],\r\n+},\r\n+{\r\n+  name: \"Saab\",\r\n+  models: [\"9-3\", \"9-5\", \"900\", \"9000\"], // legacy brand, but recognizable\r\n+},\r\n+{\r\n+  name: \"Holden\",\r\n+  models: [\"Commodore\", \"Colorado\", \"Captiva\", \"Barina\"], // Australia, discontinued but common\r\n+},\r\n+{\r\n+  name: \"Perodua\",\r\n+  models: [\"Myvi\", \"Axia\", \"Bezza\", \"Ativa\"], // Malaysia\r\n+},\r\n+{\r\n+  name: \"Proton\",\r\n+  models: [\"Saga\", \"Persona\", \"X70\", \"X50\"], // Malaysia\r\n+},\r\n+{\r\n+  name: \"Great Wall\",\r\n+  models: [\"Haval H6\", \"Haval Jolion\", \"Poer\", \"Tank 300\"], // China\r\n+},\r\n+{\r\n+  name: \"FAW\",\r\n+  models: [\"Bestune T77\", \"Bestune T99\", \"Hongqi H9\"], // China\r\n+},\r\n+{\r\n+  name: \"Dongfeng\",\r\n+  models: [\"Aeolus AX7\", \"Fengshen E70\"], // China\r\n+},\r\n+{\r\n+  name: \"SAIC Motor\",\r\n+  models: [\"MG ZS\", \"MG Hector\", \"MG5 EV\"], // Owns MG brand now\r\n+},\r\n+{\r\n+  name: \"Lada\",\r\n+  models: [\"Niva\", \"Vesta\", \"Granta\", \"XRay\"], // Russia\r\n+},\r\n+{\r\n+  name: \"UAZ\",\r\n+  models: [\"Patriot\", \"Hunter\", \"Bukhanka\"], // Russia\r\n+},\r\n+{\r\n+  name: \"Koenigsegg\",\r\n+  models: [\"Jesko\", \"Regera\", \"Agera RS\", \"Gemera\"], // Sweden supercars\r\n+},\r\n+{\r\n+  name: \"Pagani\",\r\n+  models: [\"Huayra\", \"Zonda\", \"Utopia\"], // Italy hypercars\r\n+},\r\n+{\r\n+  name: \"Fisker\",\r\n+  models: [\"Ocean\", \"Karma\", \"Ronin\"], // US EV startup\r\n+},\r\n+{\r\n+  name: \"Nikola\",\r\n+  models: [\"Tre\", \"Badger\"], // US EV/hydrogen startup\r\n+},\r\n \r\n ];\r\n \r\n export default carList;\r\n"
                },
                {
                    "date": 1758175678873,
                    "content": "Index: \n===================================================================\n--- \n+++ \n@@ -0,0 +1,488 @@\n+// carList.js\r\n+const carList = [\r\n+    {\r\n+        name: \"Honda\",\r\n+        models: [\r\n+            \"Civic\",\r\n+            \"Accord\",\r\n+            \"CR-V\",\r\n+            \"HR-V\",\r\n+            \"Pilot\",\r\n+            \"Odyssey\",\r\n+            \"Ridgeline\",\r\n+            \"Insight\",\r\n+            \"Passport\",\r\n+            \"Fit\",\r\n+        ],\r\n+    },\r\n+    {\r\n+        name: \"Toyota\",\r\n+        models: [\r\n+            \"Corolla\",\r\n+            \"Camry\",\r\n+            \"RAV4\",\r\n+            \"Highlander\",\r\n+            \"Tacoma\",\r\n+            \"Prius\",\r\n+            \"Sienna\",\r\n+            \"Tundra\",\r\n+            \"Sequoia\",\r\n+            \"Avalon\",\r\n+            \"4Runner\",\r\n+        ],\r\n+    },\r\n+    {\r\n+        name: \"Ford\",\r\n+        models: [\r\n+            \"F-150\",\r\n+            \"Escape\",\r\n+            \"Mustang\",\r\n+            \"Explorer\",\r\n+            \"Edge\",\r\n+            \"Super Duty\",\r\n+            \"Bronco\",\r\n+            \"Expedition\",\r\n+            \"Maverick\",\r\n+            \"Fusion\",\r\n+        ],\r\n+    },\r\n+    {\r\n+        name: \"Chevrolet\",\r\n+        models: [\r\n+            \"Silverado\",\r\n+            \"Equinox\",\r\n+            \"Malibu\",\r\n+            \"Traverse\",\r\n+            \"Colorado\",\r\n+            \"Bolt EV\",\r\n+            \"Spark\",\r\n+            \"Tahoe\",\r\n+            \"Suburban\",\r\n+            \"Blazer\",\r\n+        ],\r\n+    },\r\n+    {\r\n+        name: \"Hyundai\",\r\n+        models: [\r\n+            \"Kona\",\r\n+            \"Elantra\",\r\n+            \"Tucson\",\r\n+            \"Santa Fe\",\r\n+            \"Palisade\",\r\n+            \"Ioniq\",\r\n+            \"Veloster\",\r\n+            \"Sonata\",\r\n+            \"Venue\",\r\n+        ],\r\n+    },\r\n+    {\r\n+        name: \"Nissan\",\r\n+        models: [\r\n+            \"Rogue\",\r\n+            \"Altima\",\r\n+            \"Sentra\",\r\n+            \"Murano\",\r\n+            \"Frontier\",\r\n+            \"Leaf\",\r\n+            \"Kicks\",\r\n+            \"Titan\",\r\n+            \"Pathfinder\",\r\n+            \"Maxima\",\r\n+            \"Armada\",\r\n+        ],\r\n+    },\r\n+    { name: \"Ram\", models: [\"1500\", \"2500\", \"3500\", \"ProMaster\"] },\r\n+    { name: \"GMC\", models: [\"Sierra\", \"Canyon\", \"Terrain\", \"Acadia\", \"Yukon\"] },\r\n+    {\r\n+        name: \"Kia\",\r\n+        models: [\r\n+            \"Sorento\",\r\n+            \"Sportage\",\r\n+            \"Telluride\",\r\n+            \"Forte\",\r\n+            \"Soul\",\r\n+            \"K5\",\r\n+            \"Carnival\",\r\n+            \"Seltos\",\r\n+        ],\r\n+    },\r\n+    {\r\n+        name: \"Mazda\",\r\n+        models: [\r\n+            \"CX-5\",\r\n+            \"Mazda3\",\r\n+            \"CX-30\",\r\n+            \"Mazda6\",\r\n+            \"CX-9\",\r\n+            \"MX-5\",\r\n+            \"CX-50\",\r\n+            \"CX-90\",\r\n+        ],\r\n+    },\r\n+    {\r\n+        name: \"Volkswagen\",\r\n+        models: [\r\n+            \"Jetta\",\r\n+            \"Golf\",\r\n+            \"Tiguan\",\r\n+            \"Passat\",\r\n+            \"ID.4\",\r\n+            \"ID. Buzz\",\r\n+            \"Arteon\",\r\n+            \"Atlas\",\r\n+        ],\r\n+    },\r\n+    {\r\n+        name: \"BMW\",\r\n+        models: [\r\n+            \"3 Series\",\r\n+            \"X5\",\r\n+            \"X3\",\r\n+            \"5 Series\",\r\n+            \"X7\",\r\n+            \"i4\",\r\n+            \"iX\",\r\n+            \"i3\",\r\n+            \"M3\",\r\n+            \"M5\",\r\n+        ],\r\n+    },\r\n+    {\r\n+        name: \"Mercedes-Benz\",\r\n+        models: [\r\n+            \"C-Class\",\r\n+            \"GLC\",\r\n+            \"E-Class\",\r\n+            \"GLS\",\r\n+            \"EQB\",\r\n+            \"EQS\",\r\n+            \"EQE\",\r\n+            \"EQC\",\r\n+            \"S-Class\",\r\n+            \"A-Class\",\r\n+        ],\r\n+    },\r\n+    {\r\n+        name: \"Audi\",\r\n+        models: [\r\n+            \"A4\",\r\n+            \"Q5\",\r\n+            \"A3\",\r\n+            \"Q7\",\r\n+            \"e-tron\",\r\n+            \"Q4 e-tron\",\r\n+            \"Q5 e-tron\",\r\n+            \"A6 e-tron\",\r\n+            \"A8\",\r\n+        ],\r\n+    },\r\n+    {\r\n+        name: \"Tesla\",\r\n+        models: [\r\n+            \"Model 3\",\r\n+            \"Model Y\",\r\n+            \"Model S\",\r\n+            \"Model X\",\r\n+            \"Cybertruck\",\r\n+            \"Roadster\",\r\n+            \"Model S Plaid\",\r\n+        ],\r\n+    },\r\n+    {\r\n+        name: \"Jeep\",\r\n+        models: [\r\n+            \"Grand Cherokee\",\r\n+            \"Cherokee\",\r\n+            \"Wrangler\",\r\n+            \"Compass\",\r\n+            \"Gladiator\",\r\n+            \"Wagoneer\",\r\n+            \"Grand Wagoneer\",\r\n+            \"Renegade\",\r\n+        ],\r\n+    },\r\n+    {\r\n+        name: \"Subaru\",\r\n+        models: [\r\n+            \"Outback\",\r\n+            \"Forester\",\r\n+            \"Impreza\",\r\n+            \"Crosstrek\",\r\n+            \"Ascent\",\r\n+            \"WRX\",\r\n+            \"BRZ\",\r\n+            \"Legacy\",\r\n+        ],\r\n+    },\r\n+    {\r\n+        name: \"Chrysler\",\r\n+        models: [\r\n+            \"Pacifica\",\r\n+            \"Voyager\",\r\n+            \"Grand Caravan\",\r\n+            \"300\",\r\n+            \"Aspen\",\r\n+            \"Pacifica Hybrid\",\r\n+        ],\r\n+    },\r\n+    {\r\n+        name: \"Buick\",\r\n+        models: [\r\n+            \"Envision\",\r\n+            \"Encore\",\r\n+            \"Enclave\",\r\n+            \"Regal\",\r\n+            \"Cascada\",\r\n+            \"Verano\",\r\n+            \"Encore GX\",\r\n+        ],\r\n+    },\r\n+    { name: \"Lexus\", models: [\"RX\", \"NX\", \"ES\", \"UX\", \"GX\", \"LX\", \"LC\", \"IS\"] },\r\n+    {\r\n+        name: \"Porsche\",\r\n+        models: [\r\n+            \"911\",\r\n+            \"Macan\",\r\n+            \"Cayenne\",\r\n+            \"Taycan\",\r\n+            \"718 Cayman\",\r\n+            \"718 Boxster\",\r\n+            \"Panamera\",\r\n+        ],\r\n+    },\r\n+    { name: \"Acura\", models: [\"MDX\", \"RDX\", \"TLX\", \"ILX\", \"Integra\", \"NSX\"] },\r\n+    { name: \"Volvo\", models: [\"XC40\", \"XC60\", \"XC90\", \"S60\", \"S90\", \"V60\"] },\r\n+    {\r\n+        name: \"Jaguar\",\r\n+        models: [\"F-Pace\", \"E-Pace\", \"I-Pace\", \"XF\", \"XE\", \"F-Type\"],\r\n+    },\r\n+    {\r\n+        name: \"Land Rover\",\r\n+        models: [\r\n+            \"Range Rover\",\r\n+            \"Range Rover Sport\",\r\n+            \"Range Rover Velar\",\r\n+            \"Defender\",\r\n+            \"Discovery\",\r\n+        ],\r\n+    },\r\n+    {\r\n+        name: \"Mitsubishi\",\r\n+        models: [\"Outlander\", \"Eclipse Cross\", \"Mirage\", \"RVR\"],\r\n+    },\r\n+\r\n+    {\r\n+        name: \"Dodge\",\r\n+        models: [\r\n+            \"Charger\",\r\n+            \"Challenger\",\r\n+            \"Durango\",\r\n+            \"Hornet\",\r\n+            \"Journey\",\r\n+            \"Caravan\",\r\n+        ],\r\n+    },\r\n+    {\r\n+        name: \"Infiniti\",\r\n+        models: [\"Q50\", \"Q60\", \"QX50\", \"QX60\", \"QX80\"],\r\n+    },\r\n+    {\r\n+        name: \"Lincoln\",\r\n+        models: [\"Navigator\", \"Aviator\", \"Corsair\", \"Nautilus\"],\r\n+    },\r\n+    {\r\n+        name: \"Cadillac\",\r\n+        models: [\"Escalade\", \"XT5\", \"XT6\", \"Lyriq\", \"CT5\", \"CT4\"],\r\n+    },\r\n+    {\r\n+        name: \"Genesis\",\r\n+        models: [\"G70\", \"G80\", \"G90\", \"GV70\", \"GV80\"],\r\n+    },\r\n+    {\r\n+        name: \"Alfa Romeo\",\r\n+        models: [\"Giulia\", \"Stelvio\", \"Tonale\", \"4C\"],\r\n+    },\r\n+    {\r\n+        name: \"Mini\",\r\n+        models: [\"Cooper\", \"Clubman\", \"Countryman\", \"Hardtop\"],\r\n+    },\r\n+    {\r\n+        name: \"Fiat\",\r\n+        models: [\"500\", \"500X\", \"500e\", \"124 Spider\"],\r\n+    },\r\n+    {\r\n+        name: \"Peugeot\",\r\n+        models: [\"208\", \"2008\", \"3008\", \"5008\"],\r\n+    },\r\n+    {\r\n+        name: \"Renault\",\r\n+        models: [\"Clio\", \"Megane\", \"Captur\", \"Kadjar\", \"Koleos\"],\r\n+    },\r\n+    {\r\n+        name: \"Suzuki\",\r\n+        models: [\"Swift\", \"Vitara\", \"Jimny\", \"SX4\"],\r\n+    },\r\n+    {\r\n+  name: \"Maserati\",\r\n+  models: [\"Ghibli\", \"Quattroporte\", \"Levante\", \"MC20\", \"GranTurismo\"],\r\n+},\r\n+{\r\n+  name: \"Ferrari\",\r\n+  models: [\"488\", \"F8 Tributo\", \"Roma\", \"Portofino\", \"SF90 Stradale\"],\r\n+},\r\n+{\r\n+  name: \"Lamborghini\",\r\n+  models: [\"Huracán\", \"Aventador\", \"Urus\", \"Revuelto\", \"Gallardo\"],\r\n+},\r\n+{\r\n+  name: \"Aston Martin\",\r\n+  models: [\"DB11\", \"DBS\", \"Vantage\", \"DBX\", \"Valhalla\"],\r\n+},\r\n+{\r\n+  name: \"Bentley\",\r\n+  models: [\"Continental GT\", \"Flying Spur\", \"Bentayga\", \"Mulsanne\"],\r\n+},\r\n+{\r\n+  name: \"Rolls-Royce\",\r\n+  models: [\"Phantom\", \"Ghost\", \"Cullinan\", \"Wraith\", \"Dawn\"],\r\n+},\r\n+{\r\n+  name: \"Bugatti\",\r\n+  models: [\"Chiron\", \"Veyron\", \"Divo\", \"Bolide\"],\r\n+},\r\n+{\r\n+  name: \"McLaren\",\r\n+  models: [\"720S\", \"570S\", \"Artura\", \"P1\", \"GT\"],\r\n+},\r\n+{\r\n+  name: \"Polestar\",\r\n+  models: [\"Polestar 2\", \"Polestar 3\", \"Polestar 4\", \"Polestar 5\"],\r\n+},\r\n+{\r\n+  name: \"Lucid\",\r\n+  models: [\"Air\", \"Gravity\"],\r\n+},\r\n+{\r\n+  name: \"Rivian\",\r\n+  models: [\"R1T\", \"R1S\"],\r\n+},\r\n+{\r\n+  name: \"BYD\",\r\n+  models: [\"Tang\", \"Han\", \"Atto 3\", \"Dolphin\", \"Seal\"],\r\n+},\r\n+{\r\n+  name: \"Chery\",\r\n+  models: [\"Tiggo 4\", \"Tiggo 7\", \"Tiggo 8\", \"Arrizo 5\"],\r\n+},\r\n+{\r\n+  name: \"Geely\",\r\n+  models: [\"Coolray\", \"Emgrand\", \"Atlas\", \"Preface\"],\r\n+},\r\n+{\r\n+  name: \"Mahindra\",\r\n+  models: [\"XUV700\", \"Scorpio\", \"Bolero\", \"Thar\"],\r\n+},\r\n+{\r\n+  name: \"Tata\",\r\n+  models: [\"Nexon\", \"Harrier\", \"Safari\", \"Altroz\", \"Punch\"],\r\n+},\r\n+{\r\n+  name: \"Citroën\",\r\n+  models: [\"C3\", \"C4\", \"C5 Aircross\", \"Berlingo\", \"Ami\"],\r\n+},\r\n+{\r\n+  name: \"Opel\",\r\n+  models: [\"Corsa\", \"Astra\", \"Mokka\", \"Insignia\", \"Crossland\"],\r\n+},\r\n+{\r\n+  name: \"Vauxhall\",\r\n+  models: [\"Corsa\", \"Astra\", \"Mokka\", \"Crossland\"], // UK versions of Opel\r\n+},\r\n+{\r\n+  name: \"Skoda\",\r\n+  models: [\"Octavia\", \"Superb\", \"Kodiaq\", \"Kamiq\", \"Fabia\"],\r\n+},\r\n+{\r\n+  name: \"Seat\",\r\n+  models: [\"Ibiza\", \"Leon\", \"Ateca\", \"Arona\", \"Tarraco\"],\r\n+},\r\n+{\r\n+  name: \"Dacia\",\r\n+  models: [\"Duster\", \"Sandero\", \"Logan\", \"Jogger\"],\r\n+},\r\n+{\r\n+  name: \"Saab\",\r\n+  models: [\"9-3\", \"9-5\", \"900\", \"9000\"], // legacy brand, but recognizable\r\n+},\r\n+{\r\n+  name: \"Holden\",\r\n+  models: [\"Commodore\", \"Colorado\", \"Captiva\", \"Barina\"], // Australia, discontinued but common\r\n+},\r\n+{\r\n+  name: \"Perodua\",\r\n+  models: [\"Myvi\", \"Axia\", \"Bezza\", \"Ativa\"], // Malaysia\r\n+},\r\n+{\r\n+  name: \"Proton\",\r\n+  models: [\"Saga\", \"Persona\", \"X70\", \"X50\"], // Malaysia\r\n+},\r\n+{\r\n+  name: \"Great Wall\",\r\n+  models: [\"Haval H6\", \"Haval Jolion\", \"Poer\", \"Tank 300\"], // China\r\n+},\r\n+{\r\n+  name: \"FAW\",\r\n+  models: [\"Bestune T77\", \"Bestune T99\", \"Hongqi H9\"], // China\r\n+},\r\n+{\r\n+  name: \"Dongfeng\",\r\n+  models: [\"Aeolus AX7\", \"Fengshen E70\"], // China\r\n+},\r\n+{\r\n+  name: \"SAIC Motor\",\r\n+  models: [\"MG ZS\", \"MG Hector\", \"MG5 EV\"], // Owns MG brand now\r\n+},\r\n+{\r\n+  name: \"Lada\",\r\n+  models: [\"Niva\", \"Vesta\", \"Granta\", \"XRay\"], // Russia\r\n+},\r\n+{\r\n+  name: \"UAZ\",\r\n+  models: [\"Patriot\", \"Hunter\", \"Bukhanka\"], // Russia\r\n+},\r\n+{\r\n+  name: \"Koenigsegg\",\r\n+  models: [\"Jesko\", \"Regera\", \"Agera RS\", \"Gemera\"], // Sweden supercars\r\n+},\r\n+{\r\n+  name: \"Pagani\",\r\n+  models: [\"Huayra\", \"Zonda\", \"Utopia\"], // Italy hypercars\r\n+},\r\n+{\r\n+  name: \"Fisker\",\r\n+  models: [\"Ocean\", \"Karma\", \"Ronin\"], // US EV startup\r\n+},\r\n+{\r\n+  name: \"Nikola\",\r\n+  models: [\"Tre\", \"Badger\"], // US EV/hydrogen startup\r\n+},\r\n+{\r\n+  name: \"Pontiac\",\r\n+  models: [\"Firebird\", \"GTO\", \"Grand Prix\", \"Bonneville\"],\r\n+},\r\n+{\r\n+  name: \"Saturn\",\r\n+  models: [\"Ion\", \"Vue\", \"Sky\", \"Aura\"],\r\n+},\r\n+{\r\n+  name: \"Hummer\",\r\n+  models: [\"H1\", \"H2\", \"H3\", \"EV\"],\r\n+},\r\n+{\r\n+  name: \"AMC\",\r\n+  models: [\"Gremlin\", \"Pacer\", \"Javelin\", \"Eagle\"],\r\n+},\r\n+\r\n+];\r\n+\r\n+export default carList;\r\n"
                },
                {
                    "date": 1758175689993,
                    "content": "Index: \n===================================================================\n--- \n+++ \n@@ -489,8 +489,16 @@\n {\r\n   name: \"De Tomaso\",\r\n   models: [\"Pantera\", \"P72\"],\r\n },\r\n+{\r\n+  name: \"Maybach\",\r\n+  models: [\"57\", \"62\", \"S-Class Maybach\", \"GLS Maybach\"],\r\n+},\r\n+{\r\n+  name: \"Smart\",\r\n+  models: [\"Fortwo\", \"Forfour\", \"EQ Fortwo\"],\r\n+},\r\n \r\n ];\r\n \r\n export default carList;\r\n"
                },
                {
                    "date": 1758175695348,
                    "content": "Index: \n===================================================================\n--- \n+++ \n@@ -0,0 +1,512 @@\n+// carList.js\r\n+const carList = [\r\n+    {\r\n+        name: \"Honda\",\r\n+        models: [\r\n+            \"Civic\",\r\n+            \"Accord\",\r\n+            \"CR-V\",\r\n+            \"HR-V\",\r\n+            \"Pilot\",\r\n+            \"Odyssey\",\r\n+            \"Ridgeline\",\r\n+            \"Insight\",\r\n+            \"Passport\",\r\n+            \"Fit\",\r\n+        ],\r\n+    },\r\n+    {\r\n+        name: \"Toyota\",\r\n+        models: [\r\n+            \"Corolla\",\r\n+            \"Camry\",\r\n+            \"RAV4\",\r\n+            \"Highlander\",\r\n+            \"Tacoma\",\r\n+            \"Prius\",\r\n+            \"Sienna\",\r\n+            \"Tundra\",\r\n+            \"Sequoia\",\r\n+            \"Avalon\",\r\n+            \"4Runner\",\r\n+        ],\r\n+    },\r\n+    {\r\n+        name: \"Ford\",\r\n+        models: [\r\n+            \"F-150\",\r\n+            \"Escape\",\r\n+            \"Mustang\",\r\n+            \"Explorer\",\r\n+            \"Edge\",\r\n+            \"Super Duty\",\r\n+            \"Bronco\",\r\n+            \"Expedition\",\r\n+            \"Maverick\",\r\n+            \"Fusion\",\r\n+        ],\r\n+    },\r\n+    {\r\n+        name: \"Chevrolet\",\r\n+        models: [\r\n+            \"Silverado\",\r\n+            \"Equinox\",\r\n+            \"Malibu\",\r\n+            \"Traverse\",\r\n+            \"Colorado\",\r\n+            \"Bolt EV\",\r\n+            \"Spark\",\r\n+            \"Tahoe\",\r\n+            \"Suburban\",\r\n+            \"Blazer\",\r\n+        ],\r\n+    },\r\n+    {\r\n+        name: \"Hyundai\",\r\n+        models: [\r\n+            \"Kona\",\r\n+            \"Elantra\",\r\n+            \"Tucson\",\r\n+            \"Santa Fe\",\r\n+            \"Palisade\",\r\n+            \"Ioniq\",\r\n+            \"Veloster\",\r\n+            \"Sonata\",\r\n+            \"Venue\",\r\n+        ],\r\n+    },\r\n+    {\r\n+        name: \"Nissan\",\r\n+        models: [\r\n+            \"Rogue\",\r\n+            \"Altima\",\r\n+            \"Sentra\",\r\n+            \"Murano\",\r\n+            \"Frontier\",\r\n+            \"Leaf\",\r\n+            \"Kicks\",\r\n+            \"Titan\",\r\n+            \"Pathfinder\",\r\n+            \"Maxima\",\r\n+            \"Armada\",\r\n+        ],\r\n+    },\r\n+    { name: \"Ram\", models: [\"1500\", \"2500\", \"3500\", \"ProMaster\"] },\r\n+    { name: \"GMC\", models: [\"Sierra\", \"Canyon\", \"Terrain\", \"Acadia\", \"Yukon\"] },\r\n+    {\r\n+        name: \"Kia\",\r\n+        models: [\r\n+            \"Sorento\",\r\n+            \"Sportage\",\r\n+            \"Telluride\",\r\n+            \"Forte\",\r\n+            \"Soul\",\r\n+            \"K5\",\r\n+            \"Carnival\",\r\n+            \"Seltos\",\r\n+        ],\r\n+    },\r\n+    {\r\n+        name: \"Mazda\",\r\n+        models: [\r\n+            \"CX-5\",\r\n+            \"Mazda3\",\r\n+            \"CX-30\",\r\n+            \"Mazda6\",\r\n+            \"CX-9\",\r\n+            \"MX-5\",\r\n+            \"CX-50\",\r\n+            \"CX-90\",\r\n+        ],\r\n+    },\r\n+    {\r\n+        name: \"Volkswagen\",\r\n+        models: [\r\n+            \"Jetta\",\r\n+            \"Golf\",\r\n+            \"Tiguan\",\r\n+            \"Passat\",\r\n+            \"ID.4\",\r\n+            \"ID. Buzz\",\r\n+            \"Arteon\",\r\n+            \"Atlas\",\r\n+        ],\r\n+    },\r\n+    {\r\n+        name: \"BMW\",\r\n+        models: [\r\n+            \"3 Series\",\r\n+            \"X5\",\r\n+            \"X3\",\r\n+            \"5 Series\",\r\n+            \"X7\",\r\n+            \"i4\",\r\n+            \"iX\",\r\n+            \"i3\",\r\n+            \"M3\",\r\n+            \"M5\",\r\n+        ],\r\n+    },\r\n+    {\r\n+        name: \"Mercedes-Benz\",\r\n+        models: [\r\n+            \"C-Class\",\r\n+            \"GLC\",\r\n+            \"E-Class\",\r\n+            \"GLS\",\r\n+            \"EQB\",\r\n+            \"EQS\",\r\n+            \"EQE\",\r\n+            \"EQC\",\r\n+            \"S-Class\",\r\n+            \"A-Class\",\r\n+        ],\r\n+    },\r\n+    {\r\n+        name: \"Audi\",\r\n+        models: [\r\n+            \"A4\",\r\n+            \"Q5\",\r\n+            \"A3\",\r\n+            \"Q7\",\r\n+            \"e-tron\",\r\n+            \"Q4 e-tron\",\r\n+            \"Q5 e-tron\",\r\n+            \"A6 e-tron\",\r\n+            \"A8\",\r\n+        ],\r\n+    },\r\n+    {\r\n+        name: \"Tesla\",\r\n+        models: [\r\n+            \"Model 3\",\r\n+            \"Model Y\",\r\n+            \"Model S\",\r\n+            \"Model X\",\r\n+            \"Cybertruck\",\r\n+            \"Roadster\",\r\n+            \"Model S Plaid\",\r\n+        ],\r\n+    },\r\n+    {\r\n+        name: \"Jeep\",\r\n+        models: [\r\n+            \"Grand Cherokee\",\r\n+            \"Cherokee\",\r\n+            \"Wrangler\",\r\n+            \"Compass\",\r\n+            \"Gladiator\",\r\n+            \"Wagoneer\",\r\n+            \"Grand Wagoneer\",\r\n+            \"Renegade\",\r\n+        ],\r\n+    },\r\n+    {\r\n+        name: \"Subaru\",\r\n+        models: [\r\n+            \"Outback\",\r\n+            \"Forester\",\r\n+            \"Impreza\",\r\n+            \"Crosstrek\",\r\n+            \"Ascent\",\r\n+            \"WRX\",\r\n+            \"BRZ\",\r\n+            \"Legacy\",\r\n+        ],\r\n+    },\r\n+    {\r\n+        name: \"Chrysler\",\r\n+        models: [\r\n+            \"Pacifica\",\r\n+            \"Voyager\",\r\n+            \"Grand Caravan\",\r\n+            \"300\",\r\n+            \"Aspen\",\r\n+            \"Pacifica Hybrid\",\r\n+        ],\r\n+    },\r\n+    {\r\n+        name: \"Buick\",\r\n+        models: [\r\n+            \"Envision\",\r\n+            \"Encore\",\r\n+            \"Enclave\",\r\n+            \"Regal\",\r\n+            \"Cascada\",\r\n+            \"Verano\",\r\n+            \"Encore GX\",\r\n+        ],\r\n+    },\r\n+    { name: \"Lexus\", models: [\"RX\", \"NX\", \"ES\", \"UX\", \"GX\", \"LX\", \"LC\", \"IS\"] },\r\n+    {\r\n+        name: \"Porsche\",\r\n+        models: [\r\n+            \"911\",\r\n+            \"Macan\",\r\n+            \"Cayenne\",\r\n+            \"Taycan\",\r\n+            \"718 Cayman\",\r\n+            \"718 Boxster\",\r\n+            \"Panamera\",\r\n+        ],\r\n+    },\r\n+    { name: \"Acura\", models: [\"MDX\", \"RDX\", \"TLX\", \"ILX\", \"Integra\", \"NSX\"] },\r\n+    { name: \"Volvo\", models: [\"XC40\", \"XC60\", \"XC90\", \"S60\", \"S90\", \"V60\"] },\r\n+    {\r\n+        name: \"Jaguar\",\r\n+        models: [\"F-Pace\", \"E-Pace\", \"I-Pace\", \"XF\", \"XE\", \"F-Type\"],\r\n+    },\r\n+    {\r\n+        name: \"Land Rover\",\r\n+        models: [\r\n+            \"Range Rover\",\r\n+            \"Range Rover Sport\",\r\n+            \"Range Rover Velar\",\r\n+            \"Defender\",\r\n+            \"Discovery\",\r\n+        ],\r\n+    },\r\n+    {\r\n+        name: \"Mitsubishi\",\r\n+        models: [\"Outlander\", \"Eclipse Cross\", \"Mirage\", \"RVR\"],\r\n+    },\r\n+\r\n+    {\r\n+        name: \"Dodge\",\r\n+        models: [\r\n+            \"Charger\",\r\n+            \"Challenger\",\r\n+            \"Durango\",\r\n+            \"Hornet\",\r\n+            \"Journey\",\r\n+            \"Caravan\",\r\n+        ],\r\n+    },\r\n+    {\r\n+        name: \"Infiniti\",\r\n+        models: [\"Q50\", \"Q60\", \"QX50\", \"QX60\", \"QX80\"],\r\n+    },\r\n+    {\r\n+        name: \"Lincoln\",\r\n+        models: [\"Navigator\", \"Aviator\", \"Corsair\", \"Nautilus\"],\r\n+    },\r\n+    {\r\n+        name: \"Cadillac\",\r\n+        models: [\"Escalade\", \"XT5\", \"XT6\", \"Lyriq\", \"CT5\", \"CT4\"],\r\n+    },\r\n+    {\r\n+        name: \"Genesis\",\r\n+        models: [\"G70\", \"G80\", \"G90\", \"GV70\", \"GV80\"],\r\n+    },\r\n+    {\r\n+        name: \"Alfa Romeo\",\r\n+        models: [\"Giulia\", \"Stelvio\", \"Tonale\", \"4C\"],\r\n+    },\r\n+    {\r\n+        name: \"Mini\",\r\n+        models: [\"Cooper\", \"Clubman\", \"Countryman\", \"Hardtop\"],\r\n+    },\r\n+    {\r\n+        name: \"Fiat\",\r\n+        models: [\"500\", \"500X\", \"500e\", \"124 Spider\"],\r\n+    },\r\n+    {\r\n+        name: \"Peugeot\",\r\n+        models: [\"208\", \"2008\", \"3008\", \"5008\"],\r\n+    },\r\n+    {\r\n+        name: \"Renault\",\r\n+        models: [\"Clio\", \"Megane\", \"Captur\", \"Kadjar\", \"Koleos\"],\r\n+    },\r\n+    {\r\n+        name: \"Suzuki\",\r\n+        models: [\"Swift\", \"Vitara\", \"Jimny\", \"SX4\"],\r\n+    },\r\n+    {\r\n+  name: \"Maserati\",\r\n+  models: [\"Ghibli\", \"Quattroporte\", \"Levante\", \"MC20\", \"GranTurismo\"],\r\n+},\r\n+{\r\n+  name: \"Ferrari\",\r\n+  models: [\"488\", \"F8 Tributo\", \"Roma\", \"Portofino\", \"SF90 Stradale\"],\r\n+},\r\n+{\r\n+  name: \"Lamborghini\",\r\n+  models: [\"Huracán\", \"Aventador\", \"Urus\", \"Revuelto\", \"Gallardo\"],\r\n+},\r\n+{\r\n+  name: \"Aston Martin\",\r\n+  models: [\"DB11\", \"DBS\", \"Vantage\", \"DBX\", \"Valhalla\"],\r\n+},\r\n+{\r\n+  name: \"Bentley\",\r\n+  models: [\"Continental GT\", \"Flying Spur\", \"Bentayga\", \"Mulsanne\"],\r\n+},\r\n+{\r\n+  name: \"Rolls-Royce\",\r\n+  models: [\"Phantom\", \"Ghost\", \"Cullinan\", \"Wraith\", \"Dawn\"],\r\n+},\r\n+{\r\n+  name: \"Bugatti\",\r\n+  models: [\"Chiron\", \"Veyron\", \"Divo\", \"Bolide\"],\r\n+},\r\n+{\r\n+  name: \"McLaren\",\r\n+  models: [\"720S\", \"570S\", \"Artura\", \"P1\", \"GT\"],\r\n+},\r\n+{\r\n+  name: \"Polestar\",\r\n+  models: [\"Polestar 2\", \"Polestar 3\", \"Polestar 4\", \"Polestar 5\"],\r\n+},\r\n+{\r\n+  name: \"Lucid\",\r\n+  models: [\"Air\", \"Gravity\"],\r\n+},\r\n+{\r\n+  name: \"Rivian\",\r\n+  models: [\"R1T\", \"R1S\"],\r\n+},\r\n+{\r\n+  name: \"BYD\",\r\n+  models: [\"Tang\", \"Han\", \"Atto 3\", \"Dolphin\", \"Seal\"],\r\n+},\r\n+{\r\n+  name: \"Chery\",\r\n+  models: [\"Tiggo 4\", \"Tiggo 7\", \"Tiggo 8\", \"Arrizo 5\"],\r\n+},\r\n+{\r\n+  name: \"Geely\",\r\n+  models: [\"Coolray\", \"Emgrand\", \"Atlas\", \"Preface\"],\r\n+},\r\n+{\r\n+  name: \"Mahindra\",\r\n+  models: [\"XUV700\", \"Scorpio\", \"Bolero\", \"Thar\"],\r\n+},\r\n+{\r\n+  name: \"Tata\",\r\n+  models: [\"Nexon\", \"Harrier\", \"Safari\", \"Altroz\", \"Punch\"],\r\n+},\r\n+{\r\n+  name: \"Citroën\",\r\n+  models: [\"C3\", \"C4\", \"C5 Aircross\", \"Berlingo\", \"Ami\"],\r\n+},\r\n+{\r\n+  name: \"Opel\",\r\n+  models: [\"Corsa\", \"Astra\", \"Mokka\", \"Insignia\", \"Crossland\"],\r\n+},\r\n+{\r\n+  name: \"Vauxhall\",\r\n+  models: [\"Corsa\", \"Astra\", \"Mokka\", \"Crossland\"], // UK versions of Opel\r\n+},\r\n+{\r\n+  name: \"Skoda\",\r\n+  models: [\"Octavia\", \"Superb\", \"Kodiaq\", \"Kamiq\", \"Fabia\"],\r\n+},\r\n+{\r\n+  name: \"Seat\",\r\n+  models: [\"Ibiza\", \"Leon\", \"Ateca\", \"Arona\", \"Tarraco\"],\r\n+},\r\n+{\r\n+  name: \"Dacia\",\r\n+  models: [\"Duster\", \"Sandero\", \"Logan\", \"Jogger\"],\r\n+},\r\n+{\r\n+  name: \"Saab\",\r\n+  models: [\"9-3\", \"9-5\", \"900\", \"9000\"], // legacy brand, but recognizable\r\n+},\r\n+{\r\n+  name: \"Holden\",\r\n+  models: [\"Commodore\", \"Colorado\", \"Captiva\", \"Barina\"], // Australia, discontinued but common\r\n+},\r\n+{\r\n+  name: \"Perodua\",\r\n+  models: [\"Myvi\", \"Axia\", \"Bezza\", \"Ativa\"], // Malaysia\r\n+},\r\n+{\r\n+  name: \"Proton\",\r\n+  models: [\"Saga\", \"Persona\", \"X70\", \"X50\"], // Malaysia\r\n+},\r\n+{\r\n+  name: \"Great Wall\",\r\n+  models: [\"Haval H6\", \"Haval Jolion\", \"Poer\", \"Tank 300\"], // China\r\n+},\r\n+{\r\n+  name: \"FAW\",\r\n+  models: [\"Bestune T77\", \"Bestune T99\", \"Hongqi H9\"], // China\r\n+},\r\n+{\r\n+  name: \"Dongfeng\",\r\n+  models: [\"Aeolus AX7\", \"Fengshen E70\"], // China\r\n+},\r\n+{\r\n+  name: \"SAIC Motor\",\r\n+  models: [\"MG ZS\", \"MG Hector\", \"MG5 EV\"], // Owns MG brand now\r\n+},\r\n+{\r\n+  name: \"Lada\",\r\n+  models: [\"Niva\", \"Vesta\", \"Granta\", \"XRay\"], // Russia\r\n+},\r\n+{\r\n+  name: \"UAZ\",\r\n+  models: [\"Patriot\", \"Hunter\", \"Bukhanka\"], // Russia\r\n+},\r\n+{\r\n+  name: \"Koenigsegg\",\r\n+  models: [\"Jesko\", \"Regera\", \"Agera RS\", \"Gemera\"], // Sweden supercars\r\n+},\r\n+{\r\n+  name: \"Pagani\",\r\n+  models: [\"Huayra\", \"Zonda\", \"Utopia\"], // Italy hypercars\r\n+},\r\n+{\r\n+  name: \"Fisker\",\r\n+  models: [\"Ocean\", \"Karma\", \"Ronin\"], // US EV startup\r\n+},\r\n+{\r\n+  name: \"Nikola\",\r\n+  models: [\"Tre\", \"Badger\"], // US EV/hydrogen startup\r\n+},\r\n+{\r\n+  name: \"Pontiac\",\r\n+  models: [\"Firebird\", \"GTO\", \"Grand Prix\", \"Bonneville\"],\r\n+},\r\n+{\r\n+  name: \"Saturn\",\r\n+  models: [\"Ion\", \"Vue\", \"Sky\", \"Aura\"],\r\n+},\r\n+{\r\n+  name: \"Hummer\",\r\n+  models: [\"H1\", \"H2\", \"H3\", \"EV\"],\r\n+},\r\n+{\r\n+  name: \"AMC\",\r\n+  models: [\"Gremlin\", \"Pacer\", \"Javelin\", \"Eagle\"],\r\n+},\r\n+{\r\n+  name: \"Lancia\",\r\n+  models: [\"Ypsilon\", \"Delta\", \"Thema\"],\r\n+},\r\n+{\r\n+  name: \"De Tomaso\",\r\n+  models: [\"Pantera\", \"P72\"],\r\n+},\r\n+{\r\n+  name: \"Maybach\",\r\n+  models: [\"57\", \"62\", \"S-Class Maybach\", \"GLS Maybach\"],\r\n+},\r\n+{\r\n+  name: \"Smart\",\r\n+  models: [\"Fortwo\", \"Forfour\", \"EQ Fortwo\"],\r\n+},\r\n+{\r\n+  name: \"Isuzu\",\r\n+  models: [\"D-Max\", \"MU-X\", \"Trooper\", \"VehiCROSS\"],\r\n+},\r\n+{\r\n+  name: \"Daihatsu\",\r\n+  models: [\"Terios\", \"Cuore\", \"Mira\", \"Rocky\"],\r\n+},\r\n+\r\n+];\r\n+\r\n+export default carList;\r\n"
                }
            ],
            "date": 1758175270769,
            "name": "Commit-0",
            "content": "// carList.js\r\nconst carList = [\r\n  {\r\n    name: \"Honda\",\r\n    models: [\"Civic\", \"Accord\", \"CR-V\", \"HR-V\", \"Pilot\", \"Odyssey\", \"Ridgeline\", \"Insight\", \"Passport\", \"Fit\"],\r\n  },\r\n  {\r\n    name: \"Toyota\",\r\n    models: [\"Corolla\", \"Camry\", \"RAV4\", \"Highlander\", \"Tacoma\", \"Prius\", \"Sienna\", \"Tundra\", \"Sequoia\", \"Avalon\", \"4Runner\"],\r\n  },\r\n  {\r\n    name: \"Ford\",\r\n    models: [\"F-150\", \"Escape\", \"Mustang\", \"Explorer\", \"Edge\", \"Super Duty\", \"Bronco\", \"Expedition\", \"Maverick\", \"Fusion\"],\r\n  },\r\n  {\r\n    name: \"Chevrolet\",\r\n    models: [\"Silverado\", \"Equinox\", \"Malibu\", \"Traverse\", \"Colorado\", \"Bolt EV\", \"Spark\", \"Tahoe\", \"Suburban\", \"Blazer\"],\r\n  },\r\n  {\r\n    name: \"Hyundai\",\r\n    models: [\"Kona\", \"Elantra\", \"Tucson\", \"Santa Fe\", \"Palisade\", \"Ioniq\", \"Veloster\", \"Sonata\", \"Venue\"],\r\n  },\r\n  {\r\n    name: \"Nissan\",\r\n    models: [\"Rogue\", \"Altima\", \"Sentra\", \"Murano\", \"Frontier\", \"Leaf\", \"Kicks\", \"Titan\", \"Pathfinder\", \"Maxima\", \"Armada\"],\r\n  },\r\n  { name: \"Ram\", models: [\"1500\", \"2500\", \"3500\", \"ProMaster\"] },\r\n  { name: \"GMC\", models: [\"Sierra\", \"Canyon\", \"Terrain\", \"Acadia\", \"Yukon\"] },\r\n  {\r\n    name: \"Kia\",\r\n    models: [\"Sorento\", \"Sportage\", \"Telluride\", \"Forte\", \"Soul\", \"K5\", \"Carnival\", \"Seltos\"],\r\n  },\r\n  {\r\n    name: \"Mazda\",\r\n    models: [\"CX-5\", \"Mazda3\", \"CX-30\", \"Mazda6\", \"CX-9\", \"MX-5\", \"CX-50\", \"CX-90\"],\r\n  },\r\n  {\r\n    name: \"Volkswagen\",\r\n    models: [\"Jetta\", \"Golf\", \"Tiguan\", \"Passat\", \"ID.4\", \"ID. Buzz\", \"Arteon\", \"Atlas\"],\r\n  },\r\n  {\r\n    name: \"BMW\",\r\n    models: [\"3 Series\", \"X5\", \"X3\", \"5 Series\", \"X7\", \"i4\", \"iX\", \"i3\", \"M3\", \"M5\"],\r\n  },\r\n  {\r\n    name: \"Mercedes-Benz\",\r\n    models: [\"C-Class\", \"GLC\", \"E-Class\", \"GLS\", \"EQB\", \"EQS\", \"EQE\", \"EQC\", \"S-Class\", \"A-Class\"],\r\n  },\r\n  {\r\n    name: \"Audi\",\r\n    models: [\"A4\", \"Q5\", \"A3\", \"Q7\", \"e-tron\", \"Q4 e-tron\", \"Q5 e-tron\", \"A6 e-tron\", \"A8\"],\r\n  },\r\n  {\r\n    name: \"Tesla\",\r\n    models: [\"Model 3\", \"Model Y\", \"Model S\", \"Model X\", \"Cybertruck\", \"Roadster\", \"Model S Plaid\"],\r\n  },\r\n  {\r\n    name: \"Jeep\",\r\n    models: [\"Grand Cherokee\", \"Cherokee\", \"Wrangler\", \"Compass\", \"Gladiator\", \"Wagoneer\", \"Grand Wagoneer\", \"Renegade\"],\r\n  },\r\n  {\r\n    name: \"Subaru\",\r\n    models: [\"Outback\", \"Forester\", \"Impreza\", \"Crosstrek\", \"Ascent\", \"WRX\", \"BRZ\", \"Legacy\"],\r\n  },\r\n  {\r\n    name: \"Chrysler\",\r\n    models: [\"Pacifica\", \"Voyager\", \"Grand Caravan\", \"300\", \"Aspen\", \"Pacifica Hybrid\"],\r\n  },\r\n  {\r\n    name: \"Buick\",\r\n    models: [\"Envision\", \"Encore\", \"Enclave\", \"Regal\", \"Cascada\", \"Verano\", \"Encore GX\"],\r\n  },\r\n  { name: \"Lexus\", models: [\"RX\", \"NX\", \"ES\", \"UX\", \"GX\", \"LX\", \"LC\", \"IS\"] },\r\n  {\r\n    name: \"Porsche\",\r\n    models: [\"911\", \"Macan\", \"Cayenne\", \"Taycan\", \"718 Cayman\", \"718 Boxster\", \"Panamera\"],\r\n  },\r\n  { name: \"Acura\", models: [\"MDX\", \"RDX\", \"TLX\", \"ILX\", \"Integra\", \"NSX\"] },\r\n  { name: \"Volvo\", models: [\"XC40\", \"XC60\", \"XC90\", \"S60\", \"S90\", \"V60\"] },\r\n  { name: \"Jaguar\", models: [\"F-Pace\", \"E-Pace\", \"I-Pace\", \"XF\", \"XE\", \"F-Type\"] },\r\n  {\r\n    name: \"Land Rover\",\r\n    models: [\"Range Rover\", \"Range Rover Sport\", \"Range Rover Velar\", \"Defender\", \"Discovery\"],\r\n  },\r\n  { name: \"Mitsubishi\", models: [\"Outlander\", \"Eclipse Cross\", \"Mirage\", \"RVR\"] },\r\n];\r\n\r\nexport default carList;\r\n"
        }
    ]
}